CHANGELOG.txt
MANIFEST.in
README.md
setup.py
hyperion2boblight/__init__.py
hyperion2boblight/main.py
hyperion2boblight.egg-info/PKG-INFO
hyperion2boblight.egg-info/SOURCES.txt
hyperion2boblight.egg-info/dependency_links.txt
hyperion2boblight.egg-info/entry_points.txt
hyperion2boblight.egg-info/not-zip-safe
hyperion2boblight.egg-info/top_level.txt