Metadata-Version: 1.1
Name: hyperion2boblight
Version: 2.0.0
Summary: Control a Boblight server with a Hyperion client
Home-page: http://github.com/AlexisBRENON/hyperion2boblight
Author: Alexis BRENON
Author-email: brenon.alexis+hyperion2boblight@gmail.com
License: MIT
Keywords: hyperion boblight
Platform: UNKNOWN
Classifier: Development Status :: 4 - Beta
Classifier: Programming Language :: Python :: 3.5
Classifier: License :: OSI Approved :: MIT License
